README
setup.py
django_eci.egg-info/PKG-INFO
django_eci.egg-info/SOURCES.txt
django_eci.egg-info/dependency_links.txt
django_eci.egg-info/requires.txt
django_eci.egg-info/top_level.txt
eci/__init__.py
eci/admin.py
eci/get_current.py
eci/models.py
eci/utils.py