Metadata-Version: 1.0
Name: django-eci
Version: 0.1.0
Summary: European Citizen's Initiative
Home-page: http://ciin.eu/
Author: Sasha Matijasic
Author-email: sasha@selectnull.com
License: LICENSE
Platform: UNKNOWN
